k8s_graph/__init__.py
k8s_graph/builder.py
k8s_graph/export.py
k8s_graph/formatter.py
k8s_graph/models.py
k8s_graph/node_identity.py
k8s_graph/operations.py
k8s_graph/persistence.py
k8s_graph/protocols.py
k8s_graph/query.py
k8s_graph/traversal.py
k8s_graph/validator.py
k8s_graph/visualization.py
k8s_graph/adapters/__init__.py
k8s_graph/adapters/kubernetes.py
k8s_graph/discoverers/__init__.py
k8s_graph/discoverers/base.py
k8s_graph/discoverers/native.py
k8s_graph/discoverers/network.py
k8s_graph/discoverers/rbac.py
k8s_graph/discoverers/registry.py
k8s_graph/discoverers/unified.py
k8s_graph-0.1.0.dist-info/licenses/LICENSE
k8s_graph-0.1.0.dist-info/METADATA
k8s_graph-0.1.0.dist-info/WHEEL
k8s_graph-0.1.0.dist-info/top_level.txt
k8s_graph-0.1.0.dist-info/RECORD
