Metadata-Version: 2.4
Name: k8s-graph
Version: 0.1.0
Summary: Protocol-based Python library for building NetworkX graphs from Kubernetes resources
Author: Nir Adler
License-Expression: MIT
Project-URL: Homepage, https://github.com/k8s-graph/k8s-graph
Project-URL: Documentation, https://github.com/k8s-graph/k8s-graph#readme
Project-URL: Repository, https://github.com/k8s-graph/k8s-graph
Project-URL: Issues, https://github.com/k8s-graph/k8s-graph/issues
Keywords: kubernetes,k8s,graph,networkx,visualization,cloud-native
Classifier: Development Status :: 4 - Beta
Classifier: Intended Audience :: Developers
Classifier: Programming Language :: Python :: 3
Classifier: Programming Language :: Python :: 3.11
Classifier: Programming Language :: Python :: 3.12
Classifier: Programming Language :: Python :: 3.13
Classifier: Topic :: Software Development :: Libraries :: Python Modules
Classifier: Topic :: System :: Clustering
Requires-Python: >=3.11
License-File: LICENSE
Requires-Dist: networkx>=3.5
Requires-Dist: pydantic>=2.12.4
Requires-Dist: kubernetes>=34.1.0
Requires-Dist: matplotlib>=3.10.7
Requires-Dist: pygraphviz>=1.11
Provides-Extra: dev
Requires-Dist: pytest>=8.4.2; extra == "dev"
Requires-Dist: pytest-asyncio>=0.24.0; extra == "dev"
Requires-Dist: pytest-cov>=6.0.0; extra == "dev"
Requires-Dist: black>=24.0.0; extra == "dev"
Requires-Dist: ruff>=0.8.0; extra == "dev"
Requires-Dist: mypy>=1.13.0; extra == "dev"
Requires-Dist: pyvis>=0.3.2; extra == "dev"
Dynamic: license-file
